Metadata-Version: 2.1
Name: implement-pypi-example
Version: 0.0.0
Summary: Example on how to upload package on pypi
Home-page: UNKNOWN
Author: Nguyen Nguyen Nguyen
Author-email: example@example.com
License: MIT
Keywords: example
Platform: UNKNOWN
Classifier: Development Status :: 5 - Production/Stable
Classifier: Intended Audience :: Education
Classifier: Operating System :: Microsoft :: Windows :: Windows 10
Classifier: License :: OSI Approved :: MIT License
Classifier: Programming Language :: Python :: 3
License-File: LICENCE.txt
